__init__.py
inferent_deep-0.1.0.dist-info/licenses/LICENSE
inferentdeep/__init__.py
inferentdeep/training/__init__.py
inferentdeep/training/datamanager.py
inferentdeep/training/predictor.py
inferentdeep/training/preprocessor.py
inferentdeep/training/pytorch.py
tests/__init__.py
tests/test_training.py
inferent_deep-0.1.0.dist-info/METADATA
inferent_deep-0.1.0.dist-info/WHEEL
inferent_deep-0.1.0.dist-info/top_level.txt
inferent_deep-0.1.0.dist-info/RECORD
