Metadata-Version: 2.4
Name: inferent-deep
Version: 0.1.0
Summary: Inferent Ventures - Deep Learning Tools
Author-email: Inferent Ventures <inferentventures@gmail.com>
Project-URL: Homepage, https://github.com/inferent
Project-URL: Issues, https://github.com/inferent
Classifier: Programming Language :: Python :: 3
Classifier: License :: OSI Approved :: MIT License
Classifier: Operating System :: OS Independent
Requires-Python: >=3.8
License-File: LICENSE
Requires-Dist: pandas
Requires-Dist: scikit-learn
Dynamic: license-file
